[
  { "host": "tn-seed-eu.drachma.net", "port": 19335, "desc": "Foundation-operated EU DNS seed" },
  { "host": "tn-seed-us.drachma.net", "port": 19335, "desc": "Community-operated US DNS seed" },
  { "host": "tn-seed-apac.drachma.net", "port": 19335, "desc": "APAC DNS seed" },
  { "host": "tn-seed-africa.drachma.net", "port": 19335, "desc": "Africa DNS seed" },
  { "host": "tn-seed-southamerica.drachma.net", "port": 19335, "desc": "South America DNS seed" },
  { "host": "198.51.100.77", "port": 19335, "desc": "North America IPv4 bootstrap" },
  { "host": "2001:db8:abcd:1::5", "port": 19335, "desc": "IPv6 bootstrap" }
]
